siphon/__init__.py
siphon/_tools.py
siphon/_version.py
siphon/catalog.py
siphon/http_util.py
siphon/metadata.py
siphon/ncss.py
siphon/ncss_dataset.py
siphon/radarserver.py
siphon/testing.py
siphon/cdmr/__init__.py
siphon/cdmr/cdmremote.py
siphon/cdmr/cdmremotefeature.py
siphon/cdmr/cdmrfeature_pb2.py
siphon/cdmr/coveragedataset.py
siphon/cdmr/dataset.py
siphon/cdmr/ncStream_pb2.py
siphon/cdmr/ncstream.py
siphon/cdmr/xarray_support.py
siphon/simplewebservice/__init__.py
siphon/simplewebservice/acis.py
siphon/simplewebservice/iastate.py
siphon/simplewebservice/igra2.py
siphon/simplewebservice/ndbc.py
siphon/simplewebservice/wyoming.py
siphon-0.9.dist-info/AUTHORS.txt
siphon-0.9.dist-info/LICENSE
siphon-0.9.dist-info/METADATA
siphon-0.9.dist-info/WHEEL
siphon-0.9.dist-info/top_level.txt
siphon-0.9.dist-info/RECORD
