Metadata-Version: 2.1
Name: siphon
Version: 0.9
Summary: A collection of Python utilities for interacting with the Unidata technology stack.
Home-page: https://github.com/Unidata/siphon
Author: Unidata Development Team
Author-email: support-python@unidata.ucar.edu
License: BSD 3-Clause
Download-URL: https://github.com/Unidata/siphon/archive/v0.9.tar.gz
Keywords: meteorology weather
Platform: UNKNOWN
Classifier: Development Status :: 3 - Alpha
Classifier: Programming Language :: Python :: 2
Classifier: Programming Language :: Python :: 2.7
Classifier: Programming Language :: Python :: 3
Classifier: Programming Language :: Python :: 3.6
Classifier: Programming Language :: Python :: 3.7
Classifier: Topic :: Scientific/Engineering
Classifier: Intended Audience :: Science/Research
Classifier: Operating System :: OS Independent
Classifier: License :: OSI Approved :: BSD License
Requires-Python: >=2.7, !=3.0.*, !=3.1.*, !=3.2.*, !=3.3.*, !=3.4.*, !=3.5.*
Provides-Extra: netcdf
Provides-Extra: dev
Provides-Extra: test
Provides-Extra: doc
Provides-Extra: examples
